jamba_cli/__init__.py
jamba_cli/chunker.py
jamba_cli/cli.py
jamba_cli/crawler.py
jamba_cli/document.py
jamba_cli/embeddings.py
jamba_cli/rag.py
jamba_cli/settings.py
jamba_cli/setup_assets.py
jamba_cli/store.py
jambashrimp-0.1.2.dist-info/METADATA
jambashrimp-0.1.2.dist-info/WHEEL
jambashrimp-0.1.2.dist-info/entry_points.txt
jambashrimp-0.1.2.dist-info/top_level.txt
jambashrimp-0.1.2.dist-info/RECORD
