Metadata-Version: 2.4
Name: jambashrimp
Version: 0.1.2
Summary: JambaShrimp (jash): playful CLI to chat with PDFs or crawled docs using Jamba2 3B
Requires-Python: >=3.12
Requires-Dist: beautifulsoup4>=4.12.3
Requires-Dist: httpx>=0.27.2
Requires-Dist: huggingface-hub>=0.36.0
Requires-Dist: llama-cpp-python>=0.2.92
Requires-Dist: pypdf>=6.4.0
Requires-Dist: requests>=2.32.5
Requires-Dist: rich>=14.2.0
Requires-Dist: prompt-toolkit>=3.0.0
Requires-Dist: lxml>=5.3.0
Requires-Dist: numpy>=1.26.0
Requires-Dist: faiss-cpu>=1.8.0
Requires-Dist: sentence-transformers>=3.0.1
